[
  {
    "date": "2016/11",
    "authors": [
      "Patrick Wiener",
      "Manuel Stein",
      "Daniel Seebacher",
      "Julian Bruns",
      "Matthias Frank",
      "Viliam Simko",
      "Stefan Zander",
      "Jens Nimis"
    ],
    "title": "BigGIS: A Continuous Refinement Approach to Master Heterogeneity and Uncertainty in Spatio-Temporal Big Data (Vision Paper)",
    "doi": "10.1145/2996913.2996931",
    "pdf": "https://bib.dbvis.de/uploadedFiles/biggispaper.pdf",
    "event": {
      "title": "ACM SIGSPATIAL 2016 – International Conference on Advances in Geographic Information Systems",
      "url": "http://sigspatial2016.sigspatial.org/",
      "place": "San Francisco, USA",
      "when": "31.10.2016 - 03.11.2016"
    }
  },
  {
    "date": "2017/04",
    "authors": [
      "Patrick Wiener",
      "Viliam Simko",
      "Jens Nimis"
    ],
    "title": "Taming the Evolution of Big Data and its Technologies in BigGIS: A Conceptual Architectural Framework for Spatio-Temporal Analytics at Scale",
    "doi": "10.5220/0006334200900101",
    "pdf": "http://www.scitepress.org/DigitalLibrary/PublicationsDownloadPage.aspx?PaperID=30777",
    "event": {
      "title": "GISTAM 2017 – International Conference on Geographical Information Systems Theory, Applications and Management",
      "url": "http://www.gistam.org/?y=2017",
      "place": "Porto, Portugal",
      "when": "27.04.2017 - 28.04.2017"
    }
  },
  {
    "date": "2017/07",
    "authors": [
      "Julian Bruns",
      "Viliam Simko"
    ],
    "title": "Stable Hot Spot Analysis for Intra Urban Heat Islands",
    "pdf": "http://hw.oeaw.ac.at/0xc1aa500e_0x00369cbe.pdf",
    "doi": "10.1553/giscience2017_01_s79",
    "event": {
      "title": "2017 GI_Forum",
      "url": "http://epub.oeaw.ac.at/8158-3_inhalt",
      "when": "2017/01",
      "info": "Journal article"
    }
  },
  {
    "date": "2017/07",
    "authors": [
      "Joachim Rußig",
      "Julian Bruns"
    ],
    "title": "Reducing Individual Heat Stress Through Path Planning",
    "doi": "10.1553/giscience2017_01_s327",
    "pdf": "http://hw.oeaw.ac.at/0xc1aa500e_0x00369db1.pdf",
    "event": {
      "title": "2017 GI_Forum",
      "url": "http://epub.oeaw.ac.at/8158-3_inhalt",
      "when": "2017/01",
      "info": "Journal article"
    }
  },
  {
    "date": "2016/05",
    "authors": [
      "Bodo Bernsdorf",
      "Julian Bruns"
    ],
    "title": "Big-Data und Data-Mining im Umfeld städtischer Nutzungskartierung",
    "pdf": "https://amazonas.fzi.de/smw/sites/fzi.de.biggis/images/b/ba/20160512_Big-Data_und_Data-Mining.pdf",
    "event": {
      "title": "8. Dresdner Flächennutzungssymposium vom Institut für Ökologische Raumentwicklung (IÖR)",
      "url": "https://www.ioer.de/8dfns/",
      "when": "12.05.2016",
      "place": "Dresden"
    }
  },
  {
    "date": "2017/10",
    "authors": [
      "Daniel Seebacher",
      "Johannes Häußler",
      "Michael Hundt",
      "Manuel Stein",
      "Hannes Müller",
      "Ulrich Engelke",
      "Daniel Keim"
    ],
    "title": "Visual Analysis of Spatio-Temporal Event Predictions: Investigating the Spread Dynamics of Invasive Species",
    "pdf": "http://bib.dbvis.de/uploadedFiles/seebacher.pdf",
    "event": {
      "title": "Symposium on Visualization in Data Science (VDS) at IEEE VIS 2017",
      "url": "http://www.visualdatascience.org/2017/index.html",
      "when": "01.10.2017",
      "place": "Phoenix"
    }
  },
  {
    "date": "2018/10",
    "authors": [
      "Daniel Seebacher",
      "Johannes Häußler",
      "Michael Hundt",
      "Manuel Stein",
      "Hannes Müller",
      "Ulrich Engelke",
      "Daniel Keim"
    ],
    "title": "Visual Analysis of Spatio-Temporal Event Predictions: Investigating the Spread Dynamics of Invasive Species",
    "event": {
      "title": "IEEE Transactions on Big Data"
    }
  }
  
]
